deepresearch/__init__.py
deepresearch-0.0.1.dist-info/LICENSE
deepresearch-0.0.1.dist-info/METADATA
deepresearch-0.0.1.dist-info/WHEEL
deepresearch-0.0.1.dist-info/top_level.txt
deepresearch-0.0.1.dist-info/RECORD
